diffractem/__init__.py
diffractem/adxv.py
diffractem/compute.py
diffractem/dataset.py
diffractem/io.py
diffractem/legacy.py
diffractem/map_image.py
diffractem/nexus.py
diffractem/peakfinder8_extension.cpython-37m-darwin.so
diffractem/pre_proc_opts.py
diffractem/pre_process.py
diffractem/proc2d.py
diffractem/proc_peaks.py
diffractem/quick_proc.py
diffractem/stream2sol.py
diffractem/stream_convert.py
diffractem/stream_parser.py
diffractem/tools.py
diffractem/peakfinder8_extension/peakfinder8_extension.cpython-37m-darwin.so
diffractem-0.4.1.data/scripts/edview.py
diffractem-0.4.1.data/scripts/nxs2tif.py
diffractem-0.4.1.dist-info/LICENSE
diffractem-0.4.1.dist-info/METADATA
diffractem-0.4.1.dist-info/WHEEL
diffractem-0.4.1.dist-info/entry_points.txt
diffractem-0.4.1.dist-info/top_level.txt
diffractem-0.4.1.dist-info/RECORD
