Metadata-Version: 2.1
Name: diffractem
Version: 0.4.1
Summary: Some tools for working with serial electron microscopy data.
Home-page: https://github.com/robertbuecker/diffractem
Author: Robert Buecker
Author-email: robert.buecker@cssb-hamburg.de
License: UNKNOWN
Platform: UNKNOWN
Classifier: Programming Language :: Python :: 3
Classifier: License :: OSI Approved :: GNU Lesser General Public License v2 or later (LGPLv2+)
License-File: LICENSE
Requires-Dist: h5py
Requires-Dist: numpy
Requires-Dist: pandas
Requires-Dist: hdf5plugin
Requires-Dist: dask[complete]
Requires-Dist: tifffile
Requires-Dist: scipy
Requires-Dist: astropy
Requires-Dist: matplotlib
Requires-Dist: numba
Requires-Dist: pyqtgraph
Requires-Dist: pyyaml
Requires-Dist: scikit-learn
Requires-Dist: scikit-image
Requires-Dist: PyQt5
